mashrur_facebook_scraper/__init__.py
mashrur_facebook_scraper_binary-2.0.0.dist-info/METADATA
mashrur_facebook_scraper_binary-2.0.0.dist-info/WHEEL
mashrur_facebook_scraper_binary-2.0.0.dist-info/top_level.txt
mashrur_facebook_scraper_binary-2.0.0.dist-info/RECORD
