Metadata-Version: 2.4
Name: mashrur-facebook-scraper-binary
Version: 2.0.0
Summary: Professional-grade Facebook data extraction tool with Nuitka compilation support
Home-page: https://github.com/mashrur/facebook-scraper
Author: Mashrur Rahman
Author-email: mashrur.rahman@support.com
Project-URL: Bug Reports, https://github.com/mashrur/facebook-scraper/issues
Project-URL: Source, https://github.com/mashrur/facebook-scraper
Project-URL: Documentation, https://docs.mashrur-scraper.com
Keywords: facebook scraper data-extraction social-media nuitka compiled
Classifier: Development Status :: 5 - Production/Stable
Classifier: Intended Audience :: Developers
Classifier: Topic :: Software Development :: Libraries :: Python Modules
Classifier: Topic :: Internet :: WWW/HTTP :: Dynamic Content
Classifier: Programming Language :: Python :: 3
Classifier: Programming Language :: Python :: 3.7
Classifier: Programming Language :: Python :: 3.8
Classifier: Programming Language :: Python :: 3.9
Classifier: Programming Language :: Python :: 3.10
Classifier: Programming Language :: Python :: 3.11
Classifier: Programming Language :: Python :: 3.12
Classifier: Operating System :: OS Independent
Classifier: License :: Other/Proprietary License
Requires-Python: >=3.7
Requires-Dist: selenium>=4.0.0
Requires-Dist: beautifulsoup4>=4.9.0
Requires-Dist: Pillow>=8.0.0
Requires-Dist: requests>=2.25.0
Provides-Extra: compilation
Requires-Dist: nuitka>=1.8.0; extra == "compilation"
Dynamic: author
Dynamic: author-email
Dynamic: classifier
Dynamic: description
Dynamic: description-content-type
Dynamic: home-page
Dynamic: keywords
Dynamic: project-url
Dynamic: provides-extra
Dynamic: requires-dist
Dynamic: requires-python
Dynamic: summary
